  <!--Navigation Controller-->
        <scene sceneID="KfF-h7-LLj">
            <objects>
                <navigationController automaticallyAdjustsScrollViewInsets="NO" id="CiB-FX-IAm" sceneMemberID="viewController">
                    <toolbarItems/>
                    <navigationBar key="navigationBar" contentMode="scaleToFill" insetsLayoutMarginsFromSafeArea="NO" id="SJO-bH-COp">
                        <rect key="frame" x="0.0" y="0.0" width="768" height="50"/>
                        <autoresizingMask key="autoresizingMask"/>
                    </navigationBar>
                    <nil name="viewControllers"/>
                    <connections>
                        <segue destination="BYZ-38-t0r" kind="relationship" relationship="rootViewController" id="Fv4-l7-ds4"/>
                    </connections>
                </navigationController>
                <placeholder placeholderIdentifier="IBFirstResponder" id="FM2-Bt-3F7" userLabel="First Responder" customClass="UIResponder" sceneMemberID="firstResponder"/>
            </objects>
            <point key="canvasLocation" x="-406" y="102"/>
        </scene>